dj_pony/ulidfield/__init__.py
dj_pony/ulidfield/admin.py
dj_pony/ulidfield/apps.py
dj_pony/ulidfield/fields.py
dj_pony/ulidfield/forms.py
dj_pony/ulidfield/models.py
dj_pony/ulidfield/static/css/dj_pony_ulidfield.css
dj_pony/ulidfield/static/img/.gitignore
dj_pony/ulidfield/static/js/dj_pony_ulidfield.js
dj_pony/ulidfield/templates/dj_pony_ulidfield/base.html
dj_pony/ulidfield/urls.py
dj_pony/ulidfield/views.py
dj_pony.ulidfield-0.8.0.dist-info/LICENSE
dj_pony.ulidfield-0.8.0.dist-info/WHEEL
dj_pony.ulidfield-0.8.0.dist-info/METADATA
dj_pony.ulidfield-0.8.0.dist-info/RECORD
