Metadata-Version: 2.1
Name: dj-pony.ulidfield
Version: 0.8.0
Summary: A ULID Field for Django that does all the work for you.
Author: Samuel Bishop
Author-email: sam@techdragon.io
Requires-Python: >=3.6,<4.0
Classifier: Programming Language :: Python :: 3
Classifier: Programming Language :: Python :: 3.6
Classifier: Programming Language :: Python :: 3.7
Classifier: Programming Language :: Python :: 3.8
Requires-Dist: django (>=2.2)
Requires-Dist: ulid-py (>=1.0.0,<2.0.0)
